llm_rovodev.py
llm_rovodev-0.1.3.dist-info/METADATA
llm_rovodev-0.1.3.dist-info/WHEEL
llm_rovodev-0.1.3.dist-info/entry_points.txt
llm_rovodev-0.1.3.dist-info/licenses/LICENSE
llm_rovodev-0.1.3.dist-info/RECORD
