Metadata-Version: 2.4
Name: llm-rovodev
Version: 0.1.3
Summary: LLM plugin exposing the RovoDev model for the llm CLI
Project-URL: Homepage, https://github.com/possibly/llm-rovodev
Project-URL: Repository, https://github.com/possibly/llm-rovodev
Project-URL: Changelog, https://github.com/possibly/llm-rovodev/releases
Author-email: Tyler Brothers <tylerbrothers1@gmail.com>
License: Apache-2.0
License-File: LICENSE
Classifier: Intended Audience :: Developers
Classifier: License :: OSI Approved :: Apache Software License
Classifier: Programming Language :: Python
Classifier: Programming Language :: Python :: 3
Classifier: Programming Language :: Python :: 3.8
Classifier: Programming Language :: Python :: 3.9
Classifier: Programming Language :: Python :: 3.10
Classifier: Programming Language :: Python :: 3.11
Classifier: Programming Language :: Python :: 3.12
Classifier: Topic :: Software Development
Requires-Python: >=3.8
Requires-Dist: llm>=0.14.0
